note_clerk/__init__.py
note_clerk/__main__.py
note_clerk/app.py
note_clerk/checks/__init__.py
note_clerk/checks/check_filename_id.py
note_clerk/checks/check_header_tags_array.py
note_clerk/checks/check_header_tags_quoted.py
note_clerk/checks/check_header_type_leading_slash.py
note_clerk/console.py
note_clerk/fixing.py
note_clerk/linting.py
note_clerk/planning.py
note_clerk/templates/day_plan.md
note_clerk/templates/week_plan.md
note_clerk/utils.py
note_clerk-0.0.19.dist-info/entry_points.txt
note_clerk-0.0.19.dist-info/LICENSE
note_clerk-0.0.19.dist-info/WHEEL
note_clerk-0.0.19.dist-info/METADATA
note_clerk-0.0.19.dist-info/RECORD
