Metadata-Version: 2.1
Name: note-clerk
Version: 0.0.19
Summary: Utility to manage plain text notes.
Home-page: https://github.com/acjackman/note-clerk
License: MIT
Author: Adam Jackman
Author-email: adam@acjackman.com
Requires-Python: >=3.9,<4.0
Classifier: License :: OSI Approved :: MIT License
Classifier: Programming Language :: Python :: 3
Classifier: Programming Language :: Python :: 3.9
Requires-Dist: Jinja2 (>=3.0.1,<4.0.0)
Requires-Dist: boltons (>=20,<22)
Requires-Dist: click (>=7,<9)
Requires-Dist: desert (>=2020.1.6,<2021.0.0)
Requires-Dist: marshmallow (>=3.5.1,<4.0.0)
Requires-Dist: orderedset (>=2.0.3,<3.0.0)
Requires-Dist: python-dateutil (>=2.8.1,<3.0.0)
Requires-Dist: python-frontmatter (>=0.5,<1.1)
Requires-Dist: requests (>=2.23.0,<3.0.0)
Requires-Dist: ruamel.yaml (>=0.16.12,<0.17.0)
Project-URL: Documentation, https://note-clerk.readthedocs.io
Project-URL: Repository, https://github.com/acjackman/note-clerk
